gradipy/__init__.py
gradipy/datasets.py
gradipy/tensor.py
gradipy/nn/__init__.py
gradipy/nn/init.py
gradipy/nn/loss.py
gradipy/nn/optim.py
gradipy-0.1.0.dist-info/LICENSE
gradipy-0.1.0.dist-info/METADATA
gradipy-0.1.0.dist-info/WHEEL
gradipy-0.1.0.dist-info/top_level.txt
gradipy-0.1.0.dist-info/RECORD
