Metadata-Version: 2.1
Name: gradipy
Version: 0.1.0
Summary: A Lightweight Neural Network Library only using NumPy with Pytorch-like API
Home-page: https://github.com/eljanmahammadli/gradipy
Author: Eljan Mahammadli
Author-email: eljanmahammadlI@gmail.com
License: MIT
Classifier: License :: OSI Approved :: MIT License
Classifier: Programming Language :: Python :: 3
Classifier: Operating System :: OS Independent
Requires-Python: >=3.8
License-File: LICENSE
Requires-Dist: numpy >=1.26.1
Provides-Extra: dev
Requires-Dist: pytest >=7.4.3 ; extra == 'dev'
Requires-Dist: twine >=4.0.2 ; extra == 'dev'
Requires-Dist: torch >=2.1.0 ; extra == 'dev'
